{"asset_id":"btcusdt","display_name":"Bitcoin","chart_symbol":"BTCUSDT","years":[2026,2025],"primary_strategy_id":"btc_trend_b2","strategies":[{"strategy_id":"btc_hodl_b1","strategy_name":"Bitcoin \u00b7 HODL vol-targeted (B1)","strategy_type":"rule_based"},{"strategy_id":"btc_trend_b2","strategy_name":"Bitcoin \u00b7 Trend-follower Daily (B2)","strategy_type":"rule_based"},{"strategy_id":"btc_exposure_s3","strategy_name":"Bitcoin \u00b7 Regime-gated exposure (S3)","strategy_type":"hybrid"},{"strategy_id":"btc_trend_funding_s4","strategy_name":"Bitcoin \u00b7 Trend \u00d7 funding brake (S4)","strategy_type":"hybrid"}],"generated_at":"2026-07-07T01:02:52.649594+00:00"}